ai_models_panguweather/__init__.py
ai_models_panguweather/_version.py
ai_models_panguweather/model.py
ai_models_panguweather-0.0.9.dist-info/LICENSE
ai_models_panguweather-0.0.9.dist-info/METADATA
ai_models_panguweather-0.0.9.dist-info/WHEEL
ai_models_panguweather-0.0.9.dist-info/entry_points.txt
ai_models_panguweather-0.0.9.dist-info/top_level.txt
ai_models_panguweather-0.0.9.dist-info/RECORD
