Metadata-Version: 2.1
Name: ai-models-panguweather
Version: 0.0.9
Summary: An ai-models plugin to run PanguWeather
Author-email: "European Centre for Medium-Range Weather Forecasts (ECMWF)" <software.support@ecmwf.int>
License: Apache License
Project-URL: Repository, https://github.com/ecmwf-lab/ai-models-panguweather
Keywords: ai,tools
Classifier: Development Status :: 4 - Beta
Classifier: Intended Audience :: Developers
Classifier: License :: OSI Approved :: Apache Software License
Classifier: Operating System :: OS Independent
Classifier: Programming Language :: Python :: 3 :: Only
Classifier: Programming Language :: Python :: 3.9
Classifier: Programming Language :: Python :: 3.10
Classifier: Programming Language :: Python :: 3.11
Classifier: Programming Language :: Python :: 3.12
Classifier: Programming Language :: Python :: Implementation :: CPython
Classifier: Programming Language :: Python :: Implementation :: PyPy
Requires-Python: >=3.10
License-File: LICENSE
Requires-Dist: ai-models >=0.7.0
Requires-Dist: onnx
Requires-Dist: onnxruntime-silicon ; sys_platform == "darwin"
Requires-Dist: onnxruntime-gpu ; sys_platform == "linux"
Provides-Extra: dev
Requires-Dist: pre-commit ; extra == 'dev'
